setup.py
ashkatweather/__init__.py
ashkatweather/ashkatweather.py
ashkatweather.egg-info/PKG-INFO
ashkatweather.egg-info/SOURCES.txt
ashkatweather.egg-info/dependency_links.txt
ashkatweather.egg-info/requires.txt
ashkatweather.egg-info/top_level.txt