Metadata-Version: 2.1
Name: ashkatweather
Version: 1.0.0
Summary: weather forcast data for 12h
Home-page: http://example.com/
Author: AshKatLuck
Author-email: ashaluckinsanoop@gmail.com
License: MIT
Keywords: weather,forecast,openweather
Platform: UNKNOWN
Classifier: Development Status :: 3 - Alpha
Classifier: Intended Audience :: Developers
Classifier: Topic :: Software Development :: Build Tools
Classifier: License :: OSI Approved :: MIT License
Classifier: Programming Language :: Python :: 3.5
Classifier: Programming Language :: Python :: 3.6
Classifier: Programming Language :: Python :: 3.7
Classifier: Programming Language :: Python :: 3.8
